csv2ofx/__init__.py
csv2ofx/__main__.py
csv2ofx/main.py
csv2ofx/ofx.py
csv2ofx/qif.py
csv2ofx/utils.py
csv2ofx/mappings/__init__.py
csv2ofx/mappings/abnamro.py
csv2ofx/mappings/amazon.py
csv2ofx/mappings/boursorama.py
csv2ofx/mappings/capitalone.py
csv2ofx/mappings/creditunion.py
csv2ofx/mappings/custom.py
csv2ofx/mappings/default.py
csv2ofx/mappings/eqbank.py
csv2ofx/mappings/exim.py
csv2ofx/mappings/gls.py
csv2ofx/mappings/ingdirect.py
csv2ofx/mappings/ingesp.py
csv2ofx/mappings/mdb.py
csv2ofx/mappings/mint.py
csv2ofx/mappings/mint_extra.py
csv2ofx/mappings/mint_headerless.py
csv2ofx/mappings/mintapi.py
csv2ofx/mappings/msmoneyreport.py
csv2ofx/mappings/n26.py
csv2ofx/mappings/outbank.py
csv2ofx/mappings/payoneer.py
csv2ofx/mappings/pcmastercard.py
csv2ofx/mappings/rabobank.py
csv2ofx/mappings/schwabchecking.py
csv2ofx/mappings/split_account.py
csv2ofx/mappings/starling.py
csv2ofx/mappings/stripe.py
csv2ofx/mappings/ubs-ch-fr.py
csv2ofx/mappings/ubs.py
csv2ofx/mappings/xero.py
csv2ofx/mappings/yodlee.py
csv2ofx-0.34.1.dist-info/licenses/LICENSE
csv2ofx-0.34.1.dist-info/METADATA
csv2ofx-0.34.1.dist-info/WHEEL
csv2ofx-0.34.1.dist-info/entry_points.txt
csv2ofx-0.34.1.dist-info/top_level.txt
csv2ofx-0.34.1.dist-info/RECORD
