Metadata-Version: 2.4
Name: csv2ofx
Version: 0.34.1
Summary: converts a csv file of transactions to an ofx or qif file
Author-email: Reuben Cummings <reubano@gmail.com>
Maintainer-email: "Jason R. Coombs" <jaraco@jaraco.com>
Project-URL: Source, https://github.com/reubano/csv2ofx
Classifier: Development Status :: 5 - Production/Stable
Classifier: Natural Language :: English
Classifier: Programming Language :: Python :: 3
Classifier: Programming Language :: Python :: 3 :: Only
Classifier: Programming Language :: Python :: Implementation :: CPython
Classifier: Programming Language :: Python :: Implementation :: PyPy
Classifier: Environment :: Console
Classifier: Topic :: Software Development :: Libraries :: Python Modules
Classifier: Intended Audience :: Developers
Requires-Python: >=3.9
License-File: LICENSE
Requires-Dist: python-dateutil<3.0.0,>=2.7.2
Requires-Dist: requests<3.0.0,>=2.18.4
Requires-Dist: meza<0.48.0,>=0.47.0
Provides-Extra: test
Requires-Dist: pytest; extra == "test"
Requires-Dist: pytest-enabler; extra == "test"
Requires-Dist: pytest-ruff; extra == "test"
Requires-Dist: freezegun; extra == "test"
Requires-Dist: pytest-lazy-fixtures; extra == "test"
Dynamic: license-file
